pybroadlink/__init__.py
pybroadlink/asyncio_udp.py
pybroadlink/broadlink_udp.py
pybroadlink/const.py
pybroadlink-1.5.dist-info/LICENSE
pybroadlink-1.5.dist-info/METADATA
pybroadlink-1.5.dist-info/WHEEL
pybroadlink-1.5.dist-info/top_level.txt
pybroadlink-1.5.dist-info/RECORD
