Metadata-Version: 2.1
Name: pybroadlink
Version: 1.5
Summary: Asyncio module for Broadlink devices control
Home-page: https://github.com/p3g4asus/pybroadlink
Author: p3g4asus
Author-email: fulminedipegasus@gmail.com
License: UNKNOWN
Platform: UNKNOWN
Classifier: Programming Language :: Python :: 3
Classifier: License :: OSI Approved :: MIT License
Classifier: Operating System :: OS Independent
